Workbook
Name AppliedStatus: Lists!$K$1:$K$10
Name Categoreis: Lists!#REF!
Name Categories: Lists!$A$1:$A$15
Name Choice: Lists!$I$1:$I$2
Name CommitmentStatus: Lists!$I$7:$I$8
Name GoalStatus: Lists!$G$10:$G$13
Name GoalType: Lists!$E$10:$E$16
Name IncomeCategory: Lists!$C$7:$C$16
Name IncomeStatus: Lists!$I$4:$I$5
Name InterviewResult: Lists!$M$1:$M$3
Name InterviewRound: Lists!$O$1:$O$5
Name LiabilityType: Lists!$I$15:$I$25
Name LoanCategory: Lists!$J$15:$J$25
Name LoanType: Lists!$A$18:$A$23
Name NeedWant: Lists!$C$1:$C$2
Name NextAction: Lists!$Q$1:$Q$7
Name PaymentMode: Lists!$E$1:$E$4
Name Priority: Lists!$F$10:$F$12
Name TransactionTe: Lists!#REF!
Name TransactionType: Lists!$G$1:$G$4
Name v: Lists!#REF!

Sheet Plan
A1: August Financial Plan
A3: Item | B3: Amount
A4: Salary(TP) | B4: 22000
A5: Salary(TaskUS) | B5: 23000
A6: Salary(R1M) | B6: 28000
A7: EMI | B7: 8600
A8: Rent | B8: 8000
A9: Food | B9: 5000
A10: Travel | B10: 1500
A11: Misc | B11: 1000
A12: Total Expenses | B12: =SUM(B7:B11) -> 24100
A16: Scenario | B16: Money Left | C16: With Freelance
A17: TP | B17: =B4-B12 -> -2100 | C17: =B17+$B$24 -> 2900
A18: TaskUS | B18: =B5-B12 -> -1100 | C18: =B18+$B$24 -> 3900
A19: R1M | B19: =B6-B12 -> 3900 | C19: =B19+$B$24 -> 8900
A22: GOAL
A24: Freelance Goal | B24: 5000
A25: Emergency Fund Goal | B25: 45000
A26: Interviews this month | B26: 20
A27: Content Income Goal | B27: 1000
A30: Required Freelance | B30: =ABS(MIN(B17:B19)) -> 2100

Sheet Transactions
A1: Date | B1: Type | C1: Category | D1: Description | E1: Amount | F1: Need/Want | G1: Payment Mode | H1: Recurring
A2: 46201 | B2: Expense | C2: Food | D2: Showerma with cousins | E2: 260 | F2: Want | G2: Cash | H2: No
A3: 46204 | B3: Expense | C3: Travel | D3: rapido | E3: 40 | F3: Need | G3: Cash | H3: No
A4: 46205 | B4: Expense | C4: Travel | D4: rapido | E4: 200 | F4: Need | G4: UPI | H4: No
A5: 46205 | B5: Expense | C5: Food | D5: breakfast | E5: 60 | F5: Need | G5: Cash | H5: No

Sheet Budget Sheet
A1: Month | B1: Year | C1: Monthly_Budget
A2: 7 | B2: 2026 | C2: 8000

Sheet Financial Commitments
A1: Start Date | B1: From | C1: Type | D1: Total Amount | E1: Repaid | F1: Remaining | G1: Due Date | H1: Status | I1: commitment | J1: Monthly Payment | K1: End Date
A2: 46197 | B2: Bajaj (Chacha Ji) | C2: EMI | D2: 86000 | E2: 0 | F2: 86000 | G2: 46235 | H2: Active | I2: Laptop EMI | J2: 8600 | K2: 46447

Sheet Dashboard
A1: Pratham Finance Dashboard
A3: INCOME
A5: Selected Salary | B5: 22000
A6: Freelance Income | B6: 0
A7: Total Income | B7: =B5+B6 -> 22000
A10: Expenses
A12: Total Expenses | B12: =SUM(Transactions!$E$2:$E$100) -> 560
A13: Total Need Spend | B13: =SUMIF(Transactions!$F$2:$F$100,"Need",Transactions!$E$2:$E$100) -> 0
A14: Total Want Spend | B14: =SUMIF(Transactions!$F$2:$F$100,"Want",Transactions!$E$2:$E$100) -> 260
A15: Food Spending | B15: =SUMIF(Transactions!$C$2:$C$100,"Food",Transactions!$E$2:$E$100) -> 320
A16: Travel Spending | B16: =SUMIF(Transactions!$C$2:$C$100,"Travel",Transactions!$E$2:$E$100) -> 240
A19: Summary
A21: Current Balance | B21: =B7-B12 -> 21440
A22: Savings Rate | B22: =B21/B7% -> 97.454545
A23: Financial Health | B23: =IF(B21>=5000,"🟢 Excellent",IF(B21>=0,"🟡 Stable","🔴 Risk")) -> 🟢 Excellent
A24: Budget Status | B24: =IF(B21>=0,"✅ On Track","⚠️ Overspending") -> ✅ On Track
A27: Outstanding Commitments | B27: =SUM(FinancialCommitments[Remaining]) -> 86000
A29: Debt Free Progress | B29: =1-(SUM(FinancialCommitments[Remaining])/SUM(FinancialCommitments[Total Amount])) -> 0
A31: Net Positions | B31: =B21-B27 -> -64560

Sheet Monthly Review
A1: Month | B1: 46174
A2: Total Income
A3: Total Expenses
A4: Current Balance
A5: Savings Rate
A6: Highest Spending Category
A7: Biggest Expense
A8: Total Transactions
A9: Average Daily Spend
A10: Notes
A12: 📌 Wins This Month
A18: ⚠️ Mistakes
A24: 🎯 Goals For Next Month

Sheet Skill Tracker
A1: Skill | B1: Current | C1: Target | D1: Progress | E1: Last Practiced
A2: Excel
A3: Communication
A4: AI
A5: Git
A6: GitHub
A7: React
A8: Python
A9: Prompt Engineering
A10: UI/UX

Sheet Income
A1: Date | B1: Source | C1: Category | D1: Amount | E1: Status | F1: Recurring | G1: Notes
A2: 46204 | B2: Salary | C2: Job | D2: 22000 | E2: Received | F2: Yes | G2: First Salary
A3: 46218 | B3: Freelancing | C3: Video Editing | D3: 5000 | E3: Pending | F3: No | G3: Client A
A4: 46223 | B4: Friend Returned | C4: Recovery | D4: 2000 | E4: Received | F4: No | G4: Vivek

Sheet Financial Goals
A1: Goal | B1: Type | C1: Target Amount | D1: Current Amount | E1: Start Date | F1: Target Date | G1: Priority | H1: Status
A2: Emergency Fund | B2: Emergency | C2: 100000 | D2: 14840 | E2: 46204 | F2: 46387 | G2: High | H2: Active
A3: Business Capital | B3: Business | C3: 300000 | D3: 25000 | E3: 46204 | F3: 46568 | G3: High | H3: Active
A4: Bike | B4: Purchase | C4: 200000 | D4: 10000 | E4: 46235 | F4: 46600 | G4: Medium | H4: Active

Sheet Investments
A1: Date | B1: Investment | C1: Type | D1: Platform | E1: Invested Amount | F1: Current Value | G1: Units | H1: Return | I1: Status | J1: Notes

Sheet Liabilities
A1: Liability | B1: Category | C1: Original Loan | D1: Outstanding Balance | E1: Monthly EMI | F1: Intrest % | G1: Start Date | H1: End Date | I1: Status
A2: Laptop EMI | B2: Consumer Loan | C2: 86000 | D2: 86000 | E2: 8600 | F2: 0 | G2: 46235 | H2: 46508 | I2: Active

Sheet Assets
A1: Asset | B1: Category | C1: Purchase Value | D1: Current Value | E1: Purchase Date | F1: Status | G1: Notes
A2: Laptop | B2: Electronics | C2: 86000 | D2: 80000 | E2: 46197 | F2: Active
A3: Bike | B3: Vehicle | C3: 90000 | D3: 70000 | E3: 46174 | F3: Active
A4: Emergency Fund | B4: Cash | C4: 14840 | D4: 14840 | E4: 46220 | F4: Active

Sheet Income engine
A1: Current Situation | J1: Job Pyramid
A3: Item | B3: Value | J3: Level 1
A5: Age | B5: 24 | J5: JOB
A6: Laptop | B6: LOQ 5050
A7: Experience | B7: HealthCare Verification | J7: ↓
A8: Location | B8: Indore
A9: EMI | B9: 8600 | J9: Level 2
A10: Emergency Fund | B10: 0
J11: FREELANCING
A13: Income Sources | J13: ↓
A15: Source | B15: Probability | C15: Time | D15: Monthly Income | E15: Priority | J15: Level 3
A16: TP | B16: High | C16: Immediate | D16: 22000 | E16: ⭐⭐⭐⭐⭐
A17: TaskUS | B17: Medium | C17: 1-2 Week | D17: 23000 | E17: ⭐⭐⭐⭐ | J17: CONTENT
A18: R1M | B18: Medium | C18: 1-2 Week | D18: 28000 | E18: ⭐⭐⭐⭐
A19: Freelancing | B19: Low(initially) | C19: 1-3 Month | D19: Variable | E19: ⭐⭐⭐ | J19: ↓
A20: Content | B20: Low | C20: 6-12 Month | D20: Variable | E20: ⭐⭐
J21: Level 4
J23: AGENCY
J25: ↓
J27: Level 5
J29: PRODUCTS
J31: ↓
J33: Level 6
J35: INVESTMENTS

Sheet Carrer Tracker
A1: Company | B1: Role | C1: Salary | D1: Applied Date | E1: Interview Date | F1: Status | G1: Interview Round | H1: Result | I1: Next Action | J1: Notes | Q1: Total Companies
A2: TP | B2: Flipkart L2 | C2: 22000 | F2: To Apply | Q2: Applied
A3: TaskUS | B3: Any | C3: 23000 | F3: To Apply | Q3: Interviews
A4: R1M | B4: RM | C4: 28000 | F4: To Apply | Q4: Offers
A5: Softstandard | B5: Sourcing | C5: 20000 | F5: To Apply | Q5: Rejections

Sheet Interview Prep
A1: Topic | B1: Status | C1: Revision Date | D1: Confidence( /10) | E1: Notes
A2: Introduction
A3: Tell me about yourself
A4: Strengths
A5: Weaknesses
A6: HR Questions
A7: TP Questions
A8: TaskUS Questions
A9: R1M Questions
A10: Resume
A11: Salary Negotiation

Sheet Lists
A1: Food | C1: Need | E1: Cash | G1: Expense | I1: Yes | K1: To Apply | M1: Pending | O1: NA | Q1: Apply
A2: Travel | C2: Want | E2: UPI | G2: Income | I2: No | K2: Applied | M2: Selected | O2: HR | Q2: Follow Up
A3: Rent | E3: Card | G3: Investment | K3: HR Round | M3: Rejected | O3: Operations | Q3: Prepare
A4: EMI | E4: Bank Transfer | G4: Transfer | I4: Received | K4: Assessment | O4: Assessment | Q4: Attend Interview
A5: Shopping | I5: Pending | K5: Interview Scheduled | O5: Final | Q5: Submit Documents
A6: Entertainment | K6: Final Round | Q6: Wait
A7: Health | C7: Job | I7: Active | K7: Offer Received | Q7: Joined
A8: Education | C8: Freelancing | I8: Paid | K8: Selected
A9: Family | C9: Agency | K9: Rejected
A10: Business | C10: Trading | E10: Emergency | F10: High | G10: Active | K10: On Hold
A11: Software | C11: Affiliate | E11: Purchase | F11: Medium | G11: Completed
A12: Subscription | C12: Dividends | E12: Business | F12: Low | G12: Paused
A13: Investment | C13: Interest | E13: Investment | G13: Cancelled
A14: Freelance Expense | C14: Recovery | E14: Education
A15: Other | C15: Gift | E15: Travel | I15: Laptop EMI | J15: Consumer Loan
C16: Other | E16: Other | I16: ICICI Credit Card | J16: Credit Card
I17: SBI Home Loan | J17: Home Loan
A18: Family Loan | I18: Car Loan | J18: Vehicle Loan
A19: Friend Loan | I19: Education Loan | J19: Education Loan
A20: Credit Card | I20: Business Loan | J20: Business Loan
A21: EMI | I21: Personal Loan | J21: Personal Loan
A22: Fixed Expense | I22: Gold Loan | J22: Gold Loan
A23: Loan | I23: BNPL | J23: Buy Now Pay Later
I24: Family Loan | J24: Family Loan
I25: Other | J25: Other
